{
  "db_name": "PostgreSQL",
  "query": "SELECT * FROM rooms WHERE id = $1",
  "describe": {
    "columns": [
      {
        "ordinal": 0,
        "name": "id",
        "type_info": "Uuid"
      },
      {
        "ordinal": 1,
        "name": "name",
        "type_info": "Varchar"
      },
      {
        "ordinal": 2,
        "name": "description",
        "type_info": "Text"
      },
      {
        "ordinal": 3,
        "name": "owner",
        "type_info": "Varchar"
      },
      {
        "ordinal": 4,
        "name": "private",
        "type_info": "Bool"
      },
      {
        "ordinal": 5,
        "name": "open",
        "type_info": "Bool"
      },
      {
        "ordinal": 6,
        "name": "max_people_playing",
        "type_info": "Int4"
      },
      {
        "ordinal": 7,
        "name": "created_at",
        "type_info": "Timestamp"
      },
      {
        "ordinal": 8,
        "name": "updated_at",
        "type_info": "Timestamp"
      }
    ],
    "parameters": {
      "Left": [
        "Uuid"
      ]
    },
    "nullable": [
      false,
      false,
      true,
      false,
      false,
      false,
      false,
      false,
      false
    ]
  },
  "hash": "bca111bf0d7354e34678b81605cda681801360f32b72b977e2fd9d8105f0c3c9"
}
